Metadata-Version: 2.1
Name: remote-i2c
Version: 0.0.9
Summary: A client and server for I2C control over TCP
Home-page: https://gitlab.com/vectoridau/remote-i2c
Author: Daniel 'Vector' Kerr
Author-email: vector@vector.id.au
License: UNKNOWN
Platform: UNKNOWN
Classifier: Development Status :: 3 - Alpha
Classifier: License :: OSI Approved :: MIT License
Classifier: Natural Language :: English
Classifier: Operating System :: OS Independent
Classifier: Programming Language :: Python :: 3
Classifier: Topic :: System :: Hardware
Classifier: Topic :: System :: Networking
Classifier: Topic :: Utilities
Requires-Python: >=3
